scramblerapp/__init__.py
scramblerapp/__main__.py
scramblerapp/main.py
scramblerapp/scrambler.py
scramblerapp/dircrawler/__init__.py
scramblerapp/dircrawler/crawler.py
scramblerapp/dircrawler/datamodder.py
scramblerapp/dircrawler/filemodder.py
scramblerapp/gui/__init__.py
scramblerapp/gui/encryptiongui.py
scramblerapp/gui/instance.py
scramblerapp/utils/__init__.py
scramblerapp/utils/commoncmd.py
scramblerapp/utils/encryption.py
ScramblerApp-0.4.0.dist-info/LICENSE
ScramblerApp-0.4.0.dist-info/METADATA
ScramblerApp-0.4.0.dist-info/WHEEL
ScramblerApp-0.4.0.dist-info/entry_points.txt
ScramblerApp-0.4.0.dist-info/top_level.txt
ScramblerApp-0.4.0.dist-info/RECORD
